sanic_aioorm/__init__.py
sanic_aioorm/aiomodel.py
sanic_aioorm/core.py
sanic_aioorm/regist_mixin.py
sanic_aioorm/set_config_mixin.py
sanic_aioorm-0.0.5.data/data/requirements/requirements.txt
sanic_aioorm-0.0.5.data/data/requirements/requirements_dev.txt
sanic_aioorm-0.0.5.data/data/requirements/requirements_test.txt
sanic_aioorm-0.0.5.dist-info/DESCRIPTION.rst
sanic_aioorm-0.0.5.dist-info/METADATA
sanic_aioorm-0.0.5.dist-info/RECORD
sanic_aioorm-0.0.5.dist-info/WHEEL
sanic_aioorm-0.0.5.dist-info/metadata.json
sanic_aioorm-0.0.5.dist-info/top_level.txt
